flaxsr/__init__.py
flaxsr/_utils.py
flaxsr/layers/__init__.py
flaxsr/layers/stochastic.py
flaxsr/layers/upscale.py
flaxsr/losses/__init__.py
flaxsr/losses/adversarial_losses.py
flaxsr/losses/perceptual_losses.py
flaxsr/losses/pixel_wise_losses.py
flaxsr/losses/regularization_losses.py
flaxsr/losses/utils.py
flaxsr/models/__init__.py
flaxsr/models/edsr.py
flaxsr/models/espcn.py
flaxsr/models/fsrcnn.py
flaxsr/models/nafssr.py
flaxsr/models/ncnet.py
flaxsr/models/srcnn.py
flaxsr/models/srgan.py
flaxsr/models/vdsr.py
flaxsr/training/__init__.py
flaxsr/training/train_states.py
flaxsr/training/train_step.py
flaxsr-0.0.7.dist-info/LICENSE
flaxsr-0.0.7.dist-info/METADATA
flaxsr-0.0.7.dist-info/WHEEL
flaxsr-0.0.7.dist-info/top_level.txt
flaxsr-0.0.7.dist-info/RECORD
