Metadata-Version: 2.1
Name: flaxsr
Version: 0.0.7
Summary: Super Resolution tools with Jax/Flax
Home-page: https://github.com/dslisleedh/FlaxSR
Author: dslisleedh
Author-email: dslisleedh@gmail.com
Project-URL: Bug Tracker, https://github.com/dslisleedh/FlaxSR/issues
Classifier: Programming Language :: Python :: 3
Classifier: License :: OSI Approved :: Apache Software License
Classifier: Intended Audience :: Developers
Classifier: Intended Audience :: Science/Research
Classifier: Topic :: Scientific/Engineering :: Image Processing
Requires-Python: >=3.6
License-File: LICENSE
Requires-Dist: jax
Requires-Dist: jaxlib
Requires-Dist: flax
Requires-Dist: einops
Requires-Dist: tensorflow
Requires-Dist: numpy
Requires-Dist: optax
Requires-Dist: tqdm
